llm_markov/__init__.py
llm_markov-0.1.dist-info/LICENSE
llm_markov-0.1.dist-info/METADATA
llm_markov-0.1.dist-info/WHEEL
llm_markov-0.1.dist-info/entry_points.txt
llm_markov-0.1.dist-info/top_level.txt
llm_markov-0.1.dist-info/RECORD
