Metadata-Version: 2.1
Name: llm-markov
Version: 0.1
Summary: Plugin for LLM adding a Markov chain generating model
Home-page: https://github.com/simonw/llm-markov
Author: Simon Willison
License: Apache License, Version 2.0
Project-URL: Issues, https://github.com/simonw/llm-markov/issues
Project-URL: CI, https://github.com/simonw/llm-markov/actions
Project-URL: Changelog, https://github.com/simonw/llm-markov/releases
Classifier: License :: OSI Approved :: Apache Software License
Requires-Python: >=3.7
Provides-Extra: test
License-File: LICENSE
